{
    "title": "ATAC-seq replication quality metric",
    "description": "Schema for reporting ATAC-seq replication quality metrics",
    "id": "/profiles/atac_replication_quality_metric.json",
    "$schema": "http://json-schema.org/draft-04/schema#",
    "type": "object",
    "required": ["step_run","quality_metric_of", "award", "lab"],
    "additionalProperties": false,
    "identifyingProperties": ["uuid"],
    "mixinProperties": [
        { "$ref": "mixins.json#/schema_version" },
        { "$ref": "quality_metric.json#/properties" },
        { "$ref": "mixins.json#/uuid" },
        { "$ref": "mixins.json#/submitted"},
        { "$ref": "mixins.json#/aliases"},
        { "$ref": "mixins.json#/attribution" },
        { "$ref": "mixins.json#/standard_status"},
        { "$ref": "mixins.json#/assay" }
    ],
    "properties": {
        "schema_version": {
            "default": "1"
        },
        "reproducible_peaks": {
            "title": "Reproducible peaks",
            "description": "Number of peaks called from one replicate or pooled replicates passing reproducibility test by comparing self-pseudoreplicates or pooled pseudo-replicates.",
            "type": "integer",
            "minimum": 0
        },
        "idr_cutoff":{
            "title": "IDR cutoff",
            "description": "Irreproducible Discovery Rate (IDR) threshold used to define reproducible peaks",
            "type": "number",
            "minimum": 0,
            "maximum": 1
        },
        "rescue_ratio": {
            "title": "Rescue ratio",
            "description": "max(Np,Nt) / min (Np,Nt); Np: Pooled-pseudoreplicate consistent peaks (comparing two pseudoreplicates generated by subsampling pooled reads from Rep1 and Rep2); Nt: True Replicate consistent peaks (comparing true replicates Rep1 vs Rep2)",
            "type": "number",
            "minimum": 0
        },
        "self_consistency_ratio": {
            "title": "Self-consistency Ratio",
            "description": "max(N1,N2) / min (N1,N2); N1: Replicate 1 self-consistent peaks (comparing two pseudoreplicates generated by subsampling Rep1 reads); N2: same as N1 for Rep2",
            "type": "number",
            "minimum": 0
        },
        "reproducibility": {
            "title": "Reproducibility test",
            "type": "string",
            "description": "Reproducibility test result for this experiment",
            "enum": [
                "borderline",
                "fail",
                "pass"
            ]
        },
        "idr_dispersion_plot": {
            "title": "IDR dispersion plot",
            "description": "Rank consistency plots from the IDR framework. Upper Left: Replicate 1 peak ranks versus replicate 2 peak ranks - peaks that do not pass the specified idr threshold are colered red. Upper Right: Replicate 1 log10 peak scores versus replicate 2 log10 peak scores - peaks that do not pass the specified idr threshold are colered red. Bottom Row: Peaks rank versus idr scores are plotted in black. The overlayed boxplots display the distribution of idr values in each 5% quantile. The idr values are thresholded at the optimization precision - 1e-6 by default.",
            "type": "object",
            "additionalProperties": false,
            "attachment": true,
            "formInput": "file",
            "properties": {
                "download": {
                    "title": "File Name",
                    "type": "string"
                },
                "href": {
                    "comment": "Internal webapp URL for document file",
                    "type": "string"
                },
                "type": {
                    "title": "MIME type",
                    "type": "string",
                    "enum": [
                        "application/pdf",
                        "image/png"
                    ]
                },
                "size": {
                    "title": "File size",
                    "type": "integer",
                    "minimum": 0
                },
                "md5sum": {
                    "format": "md5sum",
                    "type": "string",
                    "title": "MD5sum"
                },
                "width": {
                    "title": "Image width",
                    "type": "integer",
                    "minimum": 0
                },
                "height": {
                    "title": "Image height",
                    "type": "integer",
                    "minimum": 0
                }
            }
        },
        "idr_parameters": {
            "title": "IDR run parameters",
            "description": "Parameters used for IDR reproducibility analysis",
            "type": "object",
            "additionalProperties": false,
            "attachment": true,
            "formInput": "file",
            "properties": {
                "download": {
                    "title": "File Name",
                    "type": "string"
                },
                "href": {
                    "comment": "Internal webapp URL for document file",
                    "type": "string"
                },
                "type": {
                    "title": "MIME type",
                    "type": "string",
                    "enum": [
                        "text/plain"
                    ]
                },
                "size": {
                    "title": "File size",
                    "type": "integer",
                    "minimum": 0
                },
                "md5sum": {
                    "format": "md5sum",
                    "type": "string",
                    "title": "MD5sum"
                }
            }
        }
    },
    "facets": {
        "assay_term_name": {
            "title": "Assay name"
        },
        "status": {
            "title": "Status"
        }
    },
    "changelog": "/profiles/changelogs/atac_replication_quality_metric.md"
}
